hsl_builder/Base.py
hsl_builder/Button.py
hsl_builder/Carousel.py
hsl_builder/Form.py
hsl_builder/NativeAction.py
hsl_builder/Silent.py
hsl_builder/System.py
hsl_builder/Text.py
hsl_builder/__init__.py
hsl_builder/Elements/Actionable.py
hsl_builder/Elements/CarouselItem.py
hsl_builder/Elements/FormField.py
hsl_builder/Elements/SilentAction.py
hsl_builder/Elements/__init__.py
hsl_builder-0a1.dist-info/METADATA
hsl_builder-0a1.dist-info/WHEEL
hsl_builder-0a1.dist-info/top_level.txt
hsl_builder-0a1.dist-info/RECORD
