Metadata-Version: 2.1
Name: hsl-builder
Version: 0a1
Summary: HSL Builder for creating hsl elements
Home-page: https://github.com/hellohaptik/python-hsl
License: MIT
Platform: UNKNOWN
